pysgs/__init__.py
pysgs/exceptions.py
pysgs/mailer.py
pysgs/server.py
pysgs-1.2.dist-info/LICENSE
pysgs-1.2.dist-info/METADATA
pysgs-1.2.dist-info/WHEEL
pysgs-1.2.dist-info/top_level.txt
pysgs-1.2.dist-info/RECORD
