Metadata-Version: 2.1
Name: pysgs
Version: 1.2
Summary: Send messages through SendGrid using SMTP
Home-page: https://github.com/estebansolo/pysgs
Author: Esteban Solorzano
Author-email: estebansolorzano27@gmail.com
License: UNKNOWN
Platform: UNKNOWN
Classifier: Programming Language :: Python :: 3.3
Classifier: Programming Language :: Python :: 3.4
Classifier: Programming Language :: Python :: 3.5
Classifier: Programming Language :: Python :: 3.6
Classifier: Programming Language :: Python :: 3.7
Classifier: License :: OSI Approved :: MIT License
Classifier: Operating System :: OS Independent
Classifier: Intended Audience :: Developers
